<annotation verified="yes">
	<folder>2_stone</folder>
	<filename>Tensor_118.png</filename>
	<path>C:\Users\Lukinator\Downloads\2_stone\2_stone\Tensor_118.png</path>
	<source>
		<database>Unknown</database>
	</source>
	<size>
		<width>300</width>
		<height>300</height>
		<depth>3</depth>
	</size>
	<segmented>0</segmented>
	<object>
		<name>stone</name>
		<pose>Unspecified</pose>
		<truncated>0</truncated>
		<difficult>0</difficult>
		<bndbox>
			<xmin>95</xmin>
			<ymin>95</ymin>
			<xmax>242</xmax>
			<ymax>213</ymax>
		</bndbox>
	</object>
</annotation>
